<?xml version="1.0" encoding="UTF-8"?>
<objects serializationModel="Studio.02.03.00">
	<object class="DataFile" id="{71e8f3e8-aceb-407b-ac56-45e187963f0d}">
		<property name="assetPath">
			<value>Music/Electronic Vol4 Music Pack/__MACOSX/Electronic Vol4 Music Pack/Gone Clubbin (RT 3.054)/._Electronic Vol4 Gone Clubbin Cut 30.wav</value>
		</property>
		<relationship name="masterAssetFolder">
			<destination>{431d6df1-3aca-401a-89a9-5c12ba7cb9da}</destination>
		</relationship>
	</object>
</objects>
