<?xml version="1.0" encoding="UTF-8"?>
<objects serializationModel="Studio.02.03.00">
	<object class="AudioFile" id="{28ee61db-b77c-4a1d-a2cf-45b8f424351d}">
		<property name="assetPath">
			<value>Game/HumanVocalizations/HumanMaleD/Wavs/voice_male_d_attack_groan_10.WAV</value>
		</property>
		<property name="frequencyInKHz">
			<value>48</value>
		</property>
		<property name="channelCount">
			<value>1</value>
		</property>
		<property name="length">
			<value>0.80474999999999997</value>
		</property>
		<relationship name="masterAssetFolder">
			<destination>{431d6df1-3aca-401a-89a9-5c12ba7cb9da}</destination>
		</relationship>
	</object>
</objects>
