<?xml version="1.0" encoding="UTF-8"?>
<objects serializationModel="Studio.02.03.00">
	<object class="AudioFile" id="{676d6583-6c49-41f8-98c4-d7a2ba5680b9}">
		<property name="assetPath">
			<value>Game/FoleySFXBundle/ObjectsonSurfaces/ObjectsonMetal/Wavs/Glass_picked_up_on_metal_1.WAV</value>
		</property>
		<property name="frequencyInKHz">
			<value>44.0999985</value>
		</property>
		<property name="channelCount">
			<value>1</value>
		</property>
		<property name="length">
			<value>1.486077097505669</value>
		</property>
		<relationship name="masterAssetFolder">
			<destination>{431d6df1-3aca-401a-89a9-5c12ba7cb9da}</destination>
		</relationship>
	</object>
</objects>
