<?xml version="1.0" encoding="UTF-8"?>
<objects serializationModel="Studio.02.03.00">
	<object class="AudioFile" id="{6953eb81-1915-4a7a-8d32-ce178ad82bf4}">
		<property name="assetPath">
			<value>Music/Horror Vol 4 Music Pack/Arrhythmia (RT 6.112)/Horror Vol4 Arrhythmia Cut 60.wav</value>
		</property>
		<property name="isStreaming">
			<value>true</value>
		</property>
		<property name="frequencyInKHz">
			<value>48</value>
		</property>
		<property name="channelCount">
			<value>2</value>
		</property>
		<property name="length">
			<value>64.047687499999995</value>
		</property>
		<relationship name="masterAssetFolder">
			<destination>{431d6df1-3aca-401a-89a9-5c12ba7cb9da}</destination>
		</relationship>
	</object>
</objects>
