<?xml version="1.0" encoding="UTF-8"?>
<objects serializationModel="Studio.02.03.00">
	<object class="AudioFile" id="{8236d543-5c6c-45b5-9771-dd7984ef9d4b}">
		<property name="assetPath">
			<value>Music/Heavy Electronic Music Pack Vol. 2/Fin (RT 4.217)/HeavyElectronic Vol2 Fin Cut 60.wav</value>
		</property>
		<property name="isStreaming">
			<value>true</value>
		</property>
		<property name="frequencyInKHz">
			<value>48</value>
		</property>
		<property name="channelCount">
			<value>2</value>
		</property>
		<property name="length">
			<value>67.373895833333336</value>
		</property>
		<relationship name="masterAssetFolder">
			<destination>{431d6df1-3aca-401a-89a9-5c12ba7cb9da}</destination>
		</relationship>
	</object>
</objects>
