<?xml version="1.0" encoding="UTF-8"?>
<objects serializationModel="Studio.02.03.00">
	<object class="AudioFile" id="{a465117e-0902-45d5-abdd-f3910615f0ec}">
		<property name="assetPath">
			<value>Game/FoleySFXBundle/ObjectsonSurfaces/ObjectsonMetal/Wavs/Metal_slide_on_metal_9.WAV</value>
		</property>
		<property name="frequencyInKHz">
			<value>44.0999985</value>
		</property>
		<property name="channelCount">
			<value>1</value>
		</property>
		<property name="length">
			<value>1.486077097505669</value>
		</property>
		<relationship name="masterAssetFolder">
			<destination>{431d6df1-3aca-401a-89a9-5c12ba7cb9da}</destination>
		</relationship>
	</object>
</objects>
