<?xml version="1.0" encoding="UTF-8"?>
<objects serializationModel="Studio.02.03.00">
	<object class="AudioFile" id="{b60aeec2-bb9b-4a7e-afc9-812bd4c38209}">
		<property name="assetPath">
			<value>Game/External_Content/Fmod_Muscle_Car_Sounds/Assets/V8_Muscle_5-0L_Classic/Interior/int_startup.WAV</value>
		</property>
		<property name="frequencyInKHz">
			<value>44.0999985</value>
		</property>
		<property name="channelCount">
			<value>2</value>
		</property>
		<property name="length">
			<value>0.80528344671201812</value>
		</property>
		<relationship name="masterAssetFolder">
			<destination>{431d6df1-3aca-401a-89a9-5c12ba7cb9da}</destination>
		</relationship>
	</object>
</objects>
