<?xml version="1.0" encoding="UTF-8"?>
<objects serializationModel="Studio.02.03.00">
	<object class="AudioFile" id="{d35405fd-aaea-4e75-9587-8515cd749927}">
		<property name="assetPath">
			<value>Game/NPCMerchants_Male/wav/03_CARL_Are_You_Gonna_Buy_Something.WAV</value>
		</property>
		<property name="frequencyInKHz">
			<value>44.0999985</value>
		</property>
		<property name="channelCount">
			<value>2</value>
		</property>
		<property name="length">
			<value>2.1183219954648527</value>
		</property>
		<relationship name="masterAssetFolder">
			<destination>{431d6df1-3aca-401a-89a9-5c12ba7cb9da}</destination>
		</relationship>
	</object>
</objects>
