<?xml version="1.0" encoding="UTF-8"?>
<objects serializationModel="Studio.02.03.00">
	<object class="AudioFile" id="{dda58c2b-eb86-48a0-b537-7515a249ac03}">
		<property name="assetPath">
			<value>Game/BleakHorizons/Maps/BaseAssets/AbandonedFactory/Audio/FootstepsMetal_01/S_FootstepsMetal_01_07_Run.WAV</value>
		</property>
		<property name="frequencyInKHz">
			<value>44.0999985</value>
		</property>
		<property name="channelCount">
			<value>1</value>
		</property>
		<property name="length">
			<value>0.35444444444444445</value>
		</property>
		<relationship name="masterAssetFolder">
			<destination>{431d6df1-3aca-401a-89a9-5c12ba7cb9da}</destination>
		</relationship>
	</object>
</objects>
