<?xml version="1.0" encoding="UTF-8"?>
<objects serializationModel="Studio.02.03.00">
	<object class="AudioFile" id="{dfcbb6fc-320b-42b8-a96b-ea79fa96459a}">
		<property name="assetPath">
			<value>Medieval Fantasy SFX 2/Items &amp; Misc/Black Smith Tool A.wav</value>
		</property>
		<property name="frequencyInKHz">
			<value>44.0999985</value>
		</property>
		<property name="channelCount">
			<value>2</value>
		</property>
		<property name="length">
			<value>1.0000226757369615</value>
		</property>
		<relationship name="masterAssetFolder">
			<destination>{431d6df1-3aca-401a-89a9-5c12ba7cb9da}</destination>
		</relationship>
	</object>
</objects>
